PyKakao/__init__.py
PyKakao/api.py
PyKakao/config/__init__.py
PyKakao/config/info.py
PyKakao-0.0.7.dist-info/LICENSE
PyKakao-0.0.7.dist-info/METADATA
PyKakao-0.0.7.dist-info/WHEEL
PyKakao-0.0.7.dist-info/top_level.txt
PyKakao-0.0.7.dist-info/RECORD
