Metadata-Version: 2.1
Name: PyKakao
Version: 0.0.7
Summary: Kakao Open API Python Wrapper
Home-page: https://github.com/WooilJeong/PyKakao
Author: 정우일(Wooil Jeong)
Author-email: wooil@kakao.com
License: MIT
Classifier: Programming Language :: Python :: 3
Classifier: License :: OSI Approved :: MIT License
Classifier: Operating System :: OS Independent
License-File: LICENSE
